README.md
dash_data_table/__init__.py
dash_data_table/components/DashDataTable.py
dash_data_table/components/__init__.py
dash_data_table/components/dash_data_table.min.js
dash_data_table/components/dash_data_table.min.js.map
dash_data_table/components/metadata.json
dash_data_table/components/package-info.json
package.json
dash_data_table-0.0.6.dist-info/LICENSE
dash_data_table-0.0.6.dist-info/WHEEL
dash_data_table-0.0.6.dist-info/METADATA
dash_data_table-0.0.6.dist-info/RECORD
