Metadata-Version: 2.1
Name: dash-data-table
Version: 0.0.6
Summary: 
Author: Jakob Jul Elben
Author-email: elbenjakobjul@gmail.com
Requires-Python: >=3.7,<4.0
Classifier: Programming Language :: Python :: 3
Classifier: Programming Language :: Python :: 3.7
Classifier: Programming Language :: Python :: 3.8
Classifier: Programming Language :: Python :: 3.9
Requires-Dist: dash (>=1.19.0,<2.0.0)
